<?xml version="1.0" encoding="UTF-8"?>
<objects serializationModel="Studio.02.03.00">
	<object class="AudioFile" id="{c1adf5a4-eb52-4c3f-8ff4-6a7517acde93}">
		<property name="assetPath">
			<value>PlaceholderAudio/400 Sounds Pack/Musical Effects/brass_level_start.wav</value>
		</property>
		<property name="frequencyInKHz">
			<value>44.0999985</value>
		</property>
		<property name="channelCount">
			<value>2</value>
		</property>
		<property name="length">
			<value>2.099387755102041</value>
		</property>
		<relationship name="masterAssetFolder">
			<destination>{0416a77e-1925-44ad-a8f0-7e620c032a08}</destination>
		</relationship>
	</object>
</objects>
